Database_Automation/__init__.py
Database_Automation/mongo_crud.py
Database_Automation_MongoDB_By_NikhilDSouza-0.0.1.dist-info/METADATA
Database_Automation_MongoDB_By_NikhilDSouza-0.0.1.dist-info/WHEEL
Database_Automation_MongoDB_By_NikhilDSouza-0.0.1.dist-info/top_level.txt
Database_Automation_MongoDB_By_NikhilDSouza-0.0.1.dist-info/RECORD
